cocomoco/__init__.py
cocomoco/__main__.py
cocomoco/cocomoco.py
cocomoco-0.1.0.dist-info/METADATA
cocomoco-0.1.0.dist-info/WHEEL
cocomoco-0.1.0.dist-info/entry_points.txt
cocomoco-0.1.0.dist-info/top_level.txt
cocomoco-0.1.0.dist-info/RECORD
