Metadata-Version: 2.1
Name: cocomoco
Version: 0.1.0
Summary: Cocomo Metric Calculator
Home-page: http://github.com/hgn/cocomoco
Author: Hagen Paul Pfeifer
Author-email: hagen@jauu.net
License: MIT
Platform: UNKNOWN
Classifier: Development Status :: 4 - Beta
Classifier: Intended Audience :: Developers
Classifier: Topic :: Software Development :: Build Tools
Classifier: License :: OSI Approved :: MIT License
Classifier: Programming Language :: Python :: 3
Classifier: Programming Language :: Python :: 3.7
